markdown_kroki/__init__.py
markdown_kroki/extension.py
markdown_kroki/kroki.py
markdown_kroki/plugin.py
markdown_kroki-0.4.0.dist-info/METADATA
markdown_kroki-0.4.0.dist-info/WHEEL
markdown_kroki-0.4.0.dist-info/entry_points.txt
markdown_kroki-0.4.0.dist-info/licenses/LICENSE
markdown_kroki-0.4.0.dist-info/RECORD
