Metadata-Version: 2.4
Name: markdown-kroki
Version: 0.4.0
Summary: Diagram extension for Python-Markdown using Kroki server.
Project-URL: Homepage, https://github.com/hkato/markdown-kroki
Project-URL: Documentation, https://hkato.github.io/markdown-kroki/
Project-URL: Repository, https://github.com/hkato/markdown-kroki
Project-URL: Issues, https://github.com/hkato/markdown-kroki/issues
Project-URL: Changelog, https://github.com/hkato/markdown-kroki/blob/main/CHANGELOG.md
Author-email: Hideyuki KATO <hideyuki@kato.jp>
License-Expression: MIT
License-File: LICENSE
Keywords: diagram,markdown,mermaid,mkdocs,plantuml
Classifier: Development Status :: 4 - Beta
Classifier: Intended Audience :: Developers
Classifier: Programming Language :: Python :: 3
Classifier: Programming Language :: Python :: 3.9
Classifier: Programming Language :: Python :: 3.10
Classifier: Programming Language :: Python :: 3.11
Classifier: Programming Language :: Python :: 3.12
Classifier: Programming Language :: Python :: 3.13
Classifier: Topic :: Documentation
Classifier: Topic :: Software Development :: Documentation
Requires-Python: >=3.9
Requires-Dist: markdown>=3.8
Requires-Dist: requests>=2.32.3
